[
    {
      "title": "Business Networking Meetup",
      "date": "2026-04-05",
      "location": "Benin City",
      "description": "Connect with local entrepreneurs and build valuable business relationships.",
      "image": "https://encrypted-tbn0.gstatic.com/images?q=tbn:ANd9GcTm6gx2hE582ObzWx6Dntzyir-WI8QvwzPXwQ&s"
    },
    {
      "title": "Digital Marketing Training",
      "date": "2026-04-15",
      "location": "Oredo",
      "description": "Learn how to promote your business online using modern digital tools.",
      "image": "https://elements-resized.envatousercontent.com/envato-dam-assets-production/bf1c8381-32aa-4189-aaf6-1c4bd8917591/b51107de-c227-4171-a7de-d7d866c37359.jpg?w=500&cf_fit=scale-down&mark-alpha=18&mark=https%3A%2F%2Felements-assets.envato.com%2Fstatic%2Fwatermark4.png&q=85&format=auto&s=eb64d1ba0df2c92ae37b67ff4800d15a83b2c3b1bfbebb8a96c04294587379ce"
    },
    {
      "title": "Oredo Trade Fair",
      "date": "2026-04-25",
      "location": "Samuel Ogbemudia Stadium",
      "description": "Showcase your products and services to the public and investors.",
      "image": "https://encrypted-tbn0.gstatic.com/images?q=tbn:ANd9GcRqV4tNKu1C9amyTsUM1Poce-xbeiuyu_e66Q&s"
    }
]